ekaros/__init__.py
ekaros/constants.py
ekaros/core.py
ekaros/experiment.py
ekaros/polling_client.py
ekaros/sse_client.py
ekaros/backends/__init__.py
ekaros/backends/django/__init__.py
ekaros/backends/django/_views.py
ekaros/backends/django/backend.py
ekaros/backends/django/urls.py
ekaros/utils/__init__.py
ekaros/utils/exceptions.py
ekaros/utils/types.py
ekaros_sdk-0.1.2.dist-info/licenses/LICENSE
ekaros_sdk-0.1.2.dist-info/METADATA
ekaros_sdk-0.1.2.dist-info/WHEEL
ekaros_sdk-0.1.2.dist-info/top_level.txt
ekaros_sdk-0.1.2.dist-info/RECORD
