Metadata-Version: 2.4
Name: ekaros-sdk
Version: 0.1.2
Summary: Ekaros SDK for API performance monitoring, A/B testing, and experimentation
Author-email: Anirudh Ramadurgam Venkat <anirudh@ekaros.dev>
License: MIT
Project-URL: Homepage, https://ekaros.dev/
Project-URL: Documentation, https://ekaros.dev/documentation/human/sdk/python/
Project-URL: Repository, https://github.com/Anirudh-RV/ekaros-sdk-python
Project-URL: Bug Tracker, https://github.com/Anirudh-RV/ekaros-sdk-python/issues
Keywords: django,api,monitoring,performance,ab-testing,experimentation
Classifier: Development Status :: 3 - Alpha
Classifier: Intended Audience :: Developers
Classifier: License :: OSI Approved :: MIT License
Classifier: Programming Language :: Python :: 3
Classifier: Programming Language :: Python :: 3.8
Classifier: Programming Language :: Python :: 3.9
Classifier: Programming Language :: Python :: 3.10
Classifier: Programming Language :: Python :: 3.11
Classifier: Programming Language :: Python :: 3.12
Classifier: Framework :: Django
Classifier: Framework :: Django :: 3.2
Classifier: Framework :: Django :: 4.0
Classifier: Framework :: Django :: 4.1
Classifier: Framework :: Django :: 4.2
Classifier: Framework :: Django :: 5.0
Classifier: Topic :: Software Development :: Libraries :: Python Modules
Classifier: Topic :: Internet :: WWW/HTTP
Requires-Python: >=3.8
License-File: LICENSE
Requires-Dist: requests>=2.25.0
Requires-Dist: Django>=5.0
Provides-Extra: dev
Requires-Dist: pytest>=9.0; extra == "dev"
Requires-Dist: pytest-django>=4.5; extra == "dev"
Requires-Dist: black>=25.0; extra == "dev"
Requires-Dist: flake8>=7.3; extra == "dev"
Requires-Dist: mypy>=1.19; extra == "dev"
Requires-Dist: build>=1.3; extra == "dev"
Requires-Dist: twine>=6.0.0; extra == "dev"
Dynamic: license-file
